LICENSE
README.md
klocmod/__init__.py
klocmod/internals.py
klocmod-0.3.1.dist-info/LICENSE
klocmod-0.3.1.dist-info/METADATA
klocmod-0.3.1.dist-info/WHEEL
klocmod-0.3.1.dist-info/RECORD
