Metadata-Version: 2.1
Name: klocmod
Version: 0.3.1
Summary: A simple module providing facilities to localize small programs via textual files.
Home-page: https://kozalo.ru/#post-1541257200
License: MIT
Keywords: localization library
Author: Leonid Kozarin
Author-email: kozalo@sadbot.ru
Requires-Python: >=3.8,<4.0
Classifier: Development Status :: 4 - Beta
Classifier: Intended Audience :: Developers
Classifier: License :: OSI Approved :: MIT License
Classifier: Natural Language :: English
Classifier: Operating System :: OS Independent
Classifier: Programming Language :: Python :: 3
Classifier: Programming Language :: Python :: 3.8
Classifier: Programming Language :: Python :: 3.9
Classifier: Programming Language :: Python :: 3.10
Classifier: Programming Language :: Python :: 3.11
Classifier: Programming Language :: Python :: 3
Classifier: Topic :: Software Development :: Internationalization
Classifier: Topic :: Software Development :: Libraries
Provides-Extra: yaml
Requires-Dist: pyyaml (>=6.0,<7.0) ; extra == "yaml"
Project-URL: Documentation, https://klocmod.readthedocs.io/en/latest/
Project-URL: Repository, https://github.com/kozalosev/klocmod
